hyperbeepy-0.3.1.dist-info/METADATA
hyperbeepy-0.3.1.dist-info/WHEEL
hyperbee/__init__.py
hyperbee/hyperbee.py
hyperbee/libhyperbee.so
hyperbeepy-0.3.1.dist-info/RECORD
