Metadata-Version: 2.3
Name: hyperbeepy
Version: 0.3.1
Summary: Peer to Peer B-tree
Keywords: dat,p2p,btree,hypercore
License: MIT OR Apache-2.0
Project-URL: Source Code, https://github.com/cowlicks/hyperbee
